{
	"LEFT": ["ORANGE", "YELLOW", "ORANGE", "GREEN", "BLUE", "GREEN", "RED", "WHITE", "RED"],
	"FRONT": ["GREEN", "GREEN", "GREEN", "RED", "WHITE", "RED", "BLUE", "BLUE", "BLUE"],
	"UPPER": ["WHITE", "YELLOW", "WHITE", "RED", "RED", "RED", "WHITE", "YELLOW", "WHITE"],
	"BOTTOM": ["YELLOW", "WHITE", "YELLOW", "ORANGE", "ORANGE", "ORANGE", "YELLOW", "WHITE", "YELLOW"],
	"RIGHT": ["RED", "WHITE", "RED", "BLUE", "GREEN", "BLUE", "ORANGE", "YELLOW", "ORANGE"],
	"BEHIND": ["BLUE", "BLUE", "BLUE", "ORANGE", "YELLOW", "ORANGE", "GREEN", "GREEN", "GREEN"],
}
